
    {
        "navigationList": [
            {
                "name": "Overviews",
                "iconClass": "far fa-sticky-note",
                "isActive": "false",
                "path": "/overview"
            },
            {
                "name": "Tasks",
                "iconClass": "far fa-clipboard",
                "isActive": "false",
                "path": "/tasks"
            },
            {
                "name": "Budget",
                "iconClass": "far fa-credit-card",
                "isActive": "false",
                "path": "/budget"
            },
            {
                "name": "Charts",
                "iconClass": "fas fa-chart-line",
                "isActive": "false",
                "path": "/charts"
            },
            {
                "name": "Calendar",
                "iconClass": "far fa-calendar",
                "isActive": "false",
                "path": "/calendar"
            }
            
        ]
    }
